{"title":"魚蛋論","slug":"魚蛋論","date":"2018-06-29T10:15:17.000Z","updated":"2018-06-29T17:45:12.092Z","comments":true,"path":"api/articles/魚蛋論.json","photos":["https://blog.sukitsuki.com/2018/06/29/魚蛋論/cjiky05ny01no6u5neo1q9git.jpg"],"link":"","excerpt":null,"covers":null,"content":"<blockquote>\n<p>魚蛋論</p>\n</blockquote>\n<p>我們買串魚蛋都是這樣：為什麼呀？為什麼大家用同樣價錢買串魚蛋，他那串魚蛋比我的多了兩粒？</p>\n<p>我不要你給回我兩粒魚蛋，我要你拿走他那兩粒！大家少兩粒，這樣就公平呀！ </p>\n<p>為什麼他有甜醬我沒有呀？ 我不要你給我甜醬，我要你舔走他那些甜醬！大家都不甜，這樣就公平呀！</p>\n<p>為什麼他沒有了甜醬，又少了兩粒，佢仍然吃得這樣開心呀？不公平！</p>\n<p>怎樣才公平呀？大家都不開心！大家都吃得很下賤啊！—— 黃華子《冇炭用》2003</p>\n<p>怎樣才算公平，自己得不到，他人也別想得到，這是不是就是公平？</p>\n<p>樂觀主意者看到半杯水，會想到還有半杯水。</p>\n<p>而悲觀主者看到半杯水，會覺得只有半杯水。</p>\n<p>突發事情，十分之討厭，為什麼生活上有這麼多不如意的事情發生呢。</p>\n<p>如果累了就停下來休息，但又有多少人能做到。</p>\n<p>如果沒有追求，沒有期望，就沒有失望。</p>\n<p><code>Advertising has us chasing cars and clothes, working jobs we hate so we can buy shit we don’t need. We’re the middle children of history, man. No purpose or place. We have no Great War. No Great Depression. Our Great War’s a spiritual war… our Great Depression is our lives.</code></p>\n<p>但也許只有失去了，在明白存在過的價值。</p>\n<blockquote>\n<p>遊戲</p>\n</blockquote>\n<p>原來PSO2六周年活動己經開始了，不過網絡實在太差，連在lobby也各種卡頓，呆了一會就下線了。</p>\n<p>Bayonetta 把難改成Easy，完全變成別一款遊戲了，感覺差距很大，先用Easy打通再說。</p>\n<p>今天打到第7關。</p>\n<blockquote>\n<p>動畫</p>\n</blockquote>\n<p>Citrus己經看完12集了，有空去看看漫畫啦。整體上故事有點刻意的感覺，也許是我的錯覺，但人總是對自己很不誠實呢。</p>\n<blockquote>\n<p>小說</p>\n</blockquote>\n<p>今天看完第一本《剃須，然後撿到女高中生》，感想是很平凡，很簡單，很感動。</p>\n<p><code>對我來說，這個家僅僅是個吃飯洗澡的空間。</code> </p>\n<p><code>因為工作有趣，越是努力工作就越能掙錢，我不討厭三點一線的生活方式。</code></p>\n<p>如果生活能簡簡單單，平凡的活著，可能是一種無知的辛褔。</p>\n","categories":[{"name":"日記","slug":"日記","count":20,"path":"api/categories/日記.json"}],"tags":[]}